zpaq.cpython-310-darwin.so
pyzpaq-0.1.10.dist-info/METADATA
pyzpaq-0.1.10.dist-info/WHEEL
pyzpaq-0.1.10.dist-info/top_level.txt
pyzpaq-0.1.10.dist-info/RECORD
