Metadata-Version: 2.1
Name: pyzpaq
Version: 0.1.10
Summary: Python zpaq bindings
Home-page: https://github.com/CPB9/pyzpaq.git
